byted_overpass_flow_dataengine_byte_rag/__init__.py
byted_overpass_flow_dataengine_byte_rag-0.0.1.dist-info/METADATA
byted_overpass_flow_dataengine_byte_rag-0.0.1.dist-info/WHEEL
byted_overpass_flow_dataengine_byte_rag-0.0.1.dist-info/top_level.txt
byted_overpass_flow_dataengine_byte_rag-0.0.1.dist-info/RECORD
